[
  {
    "Metadata": [
      {
        "Type": "WordBoundary",
        "Data": {
          "Offset": 1000000,
          "Duration": 4125000,
          "text": {
            "Text": "第三",
            "Length": 2,
            "BoundaryType": "WordBoundary"
          }
        }
      }
    ]
  },
  {
    "Metadata": [
      {
        "Type": "WordBoundary",
        "Data": {
          "Offset": 8875000,
          "Duration": 3125000,
          "text": {
            "Text": "AI",
            "Length": 2,
            "BoundaryType": "WordBoundary"
          }
        }
      }
    ]
  },
  {
    "Metadata": [
      {
        "Type": "WordBoundary",
        "Data": {
          "Offset": 12125000,
          "Duration": 4000000,
          "text": {
            "Text": "外包",
            "Length": 2,
            "BoundaryType": "WordBoundary"
          }
        }
      }
    ]
  },
  {
    "Metadata": [
      {
        "Type": "WordBoundary",
        "Data": {
          "Offset": 16250000,
          "Duration": 3625000,
          "text": {
            "Text": "工作",
            "Length": 2,
            "BoundaryType": "WordBoundary"
          }
        }
      }
    ]
  },
  {
    "Metadata": [
      {
        "Type": "WordBoundary",
        "Data": {
          "Offset": 19875000,
          "Duration": 2250000,
          "text": {
            "Text": "室",
            "Length": 1,
            "BoundaryType": "WordBoundary"
          }
        }
      }
    ]
  },
  {
    "Metadata": [
      {
        "Type": "WordBoundary",
        "Data": {
          "Offset": 25000000,
          "Duration": 2625000,
          "text": {
            "Text": "当",
            "Length": 1,
            "BoundaryType": "WordBoundary"
          }
        }
      }
    ]
  },
  {
    "Metadata": [
      {
        "Type": "WordBoundary",
        "Data": {
          "Offset": 28875000,
          "Duration": 2875000,
          "text": {
            "Text": "AI",
            "Length": 2,
            "BoundaryType": "WordBoundary"
          }
        }
      }
    ]
  },
  {
    "Metadata": [
      {
        "Type": "WordBoundary",
        "Data": {
          "Offset": 31875000,
          "Duration": 4250000,
          "text": {
            "Text": "员工",
            "Length": 2,
            "BoundaryType": "WordBoundary"
          }
        }
      }
    ]
  },
  {
    "Metadata": [
      {
        "Type": "WordBoundary",
        "Data": {
          "Offset": 41875000,
          "Duration": 2625000,
          "text": {
            "Text": "一个",
            "Length": 2,
            "BoundaryType": "WordBoundary"
          }
        }
      }
    ]
  },
  {
    "Metadata": [
      {
        "Type": "WordBoundary",
        "Data": {
          "Offset": 44500000,
          "Duration": 1125000,
          "text": {
            "Text": "人",
            "Length": 1,
            "BoundaryType": "WordBoundary"
          }
        }
      }
    ]
  },
  {
    "Metadata": [
      {
        "Type": "WordBoundary",
        "Data": {
          "Offset": 45750000,
          "Duration": 2000000,
          "text": {
            "Text": "开",
            "Length": 1,
            "BoundaryType": "WordBoundary"
          }
        }
      }
    ]
  },
  {
    "Metadata": [
      {
        "Type": "WordBoundary",
        "Data": {
          "Offset": 47750000,
          "Duration": 1375000,
          "text": {
            "Text": "的",
            "Length": 1,
            "BoundaryType": "WordBoundary"
          }
        }
      }
    ]
  },
  {
    "Metadata": [
      {
        "Type": "WordBoundary",
        "Data": {
          "Offset": 49250000,
          "Duration": 4875000,
          "text": {
            "Text": "自动化",
            "Length": 3,
            "BoundaryType": "WordBoundary"
          }
        }
      }
    ]
  },
  {
    "Metadata": [
      {
        "Type": "WordBoundary",
        "Data": {
          "Offset": 54250000,
          "Duration": 5000000,
          "text": {
            "Text": "工作室",
            "Length": 3,
            "BoundaryType": "WordBoundary"
          }
        }
      }
    ]
  },
  {
    "Metadata": [
      {
        "Type": "WordBoundary",
        "Data": {
          "Offset": 59250000,
          "Duration": 1750000,
          "text": {
            "Text": "里",
            "Length": 1,
            "BoundaryType": "WordBoundary"
          }
        }
      }
    ]
  },
  {
    "Metadata": [
      {
        "Type": "WordBoundary",
        "Data": {
          "Offset": 63750000,
          "Duration": 7000000,
          "text": {
            "Text": "OpenClaw",
            "Length": 8,
            "BoundaryType": "WordBoundary"
          }
        }
      }
    ]
  },
  {
    "Metadata": [
      {
        "Type": "WordBoundary",
        "Data": {
          "Offset": 71000000,
          "Duration": 1750000,
          "text": {
            "Text": "当",
            "Length": 1,
            "BoundaryType": "WordBoundary"
          }
        }
      }
    ]
  },
  {
    "Metadata": [
      {
        "Type": "WordBoundary",
        "Data": {
          "Offset": 72875000,
          "Duration": 4000000,
          "text": {
            "Text": "员工",
            "Length": 2,
            "BoundaryType": "WordBoundary"
          }
        }
      }
    ]
  },
  {
    "Metadata": [
      {
        "Type": "WordBoundary",
        "Data": {
          "Offset": 82625000,
          "Duration": 1500000,
          "text": {
            "Text": "它",
            "Length": 1,
            "BoundaryType": "WordBoundary"
          }
        }
      }
    ]
  },
  {
    "Metadata": [
      {
        "Type": "WordBoundary",
        "Data": {
          "Offset": 84250000,
          "Duration": 3250000,
          "text": {
            "Text": "负责",
            "Length": 2,
            "BoundaryType": "WordBoundary"
          }
        }
      }
    ]
  },
  {
    "Metadata": [
      {
        "Type": "WordBoundary",
        "Data": {
          "Offset": 87625000,
          "Duration": 2625000,
          "text": {
            "Text": "写",
            "Length": 1,
            "BoundaryType": "WordBoundary"
          }
        }
      }
    ]
  },
  {
    "Metadata": [
      {
        "Type": "WordBoundary",
        "Data": {
          "Offset": 90250000,
          "Duration": 3250000,
          "text": {
            "Text": "S",
            "Length": 1,
            "BoundaryType": "WordBoundary"
          }
        }
      }
    ]
  },
  {
    "Metadata": [
      {
        "Type": "WordBoundary",
        "Data": {
          "Offset": 93625000,
          "Duration": 1250000,
          "text": {
            "Text": "E",
            "Length": 1,
            "BoundaryType": "WordBoundary"
          }
        }
      }
    ]
  },
  {
    "Metadata": [
      {
        "Type": "WordBoundary",
        "Data": {
          "Offset": 94875000,
          "Duration": 1250000,
          "text": {
            "Text": "O",
            "Length": 1,
            "BoundaryType": "WordBoundary"
          }
        }
      }
    ]
  },
  {
    "Metadata": [
      {
        "Type": "WordBoundary",
        "Data": {
          "Offset": 96250000,
          "Duration": 3750000,
          "text": {
            "Text": "文章",
            "Length": 2,
            "BoundaryType": "WordBoundary"
          }
        }
      }
    ]
  },
  {
    "Metadata": [
      {
        "Type": "WordBoundary",
        "Data": {
          "Offset": 102500000,
          "Duration": 3500000,
          "text": {
            "Text": "回复",
            "Length": 2,
            "BoundaryType": "WordBoundary"
          }
        }
      }
    ]
  },
  {
    "Metadata": [
      {
        "Type": "WordBoundary",
        "Data": {
          "Offset": 106125000,
          "Duration": 4250000,
          "text": {
            "Text": "客服",
            "Length": 2,
            "BoundaryType": "WordBoundary"
          }
        }
      }
    ]
  },
  {
    "Metadata": [
      {
        "Type": "WordBoundary",
        "Data": {
          "Offset": 112000000,
          "Duration": 4375000,
          "text": {
            "Text": "生成",
            "Length": 2,
            "BoundaryType": "WordBoundary"
          }
        }
      }
    ]
  },
  {
    "Metadata": [
      {
        "Type": "WordBoundary",
        "Data": {
          "Offset": 116625000,
          "Duration": 4500000,
          "text": {
            "Text": "营销",
            "Length": 2,
            "BoundaryType": "WordBoundary"
          }
        }
      }
    ]
  },
  {
    "Metadata": [
      {
        "Type": "WordBoundary",
        "Data": {
          "Offset": 121250000,
          "Duration": 3500000,
          "text": {
            "Text": "文案",
            "Length": 2,
            "BoundaryType": "WordBoundary"
          }
        }
      }
    ]
  },
  {
    "Metadata": [
      {
        "Type": "WordBoundary",
        "Data": {
          "Offset": 126500000,
          "Duration": 3750000,
          "text": {
            "Text": "处理",
            "Length": 2,
            "BoundaryType": "WordBoundary"
          }
        }
      }
    ]
  },
  {
    "Metadata": [
      {
        "Type": "WordBoundary",
        "Data": {
          "Offset": 130375000,
          "Duration": 3500000,
          "text": {
            "Text": "邮件",
            "Length": 2,
            "BoundaryType": "WordBoundary"
          }
        }
      }
    ]
  },
  {
    "Metadata": [
      {
        "Type": "WordBoundary",
        "Data": {
          "Offset": 139625000,
          "Duration": 4125000,
          "text": {
            "Text": "现实",
            "Length": 2,
            "BoundaryType": "WordBoundary"
          }
        }
      }
    ]
  },
  {
    "Metadata": [
      {
        "Type": "WordBoundary",
        "Data": {
          "Offset": 143875000,
          "Duration": 2625000,
          "text": {
            "Text": "案例",
            "Length": 2,
            "BoundaryType": "WordBoundary"
          }
        }
      }
    ]
  },
  {
    "Metadata": [
      {
        "Type": "WordBoundary",
        "Data": {
          "Offset": 146500000,
          "Duration": 1750000,
          "text": {
            "Text": "中",
            "Length": 1,
            "BoundaryType": "WordBoundary"
          }
        }
      }
    ]
  },
  {
    "Metadata": [
      {
        "Type": "WordBoundary",
        "Data": {
          "Offset": 151250000,
          "Duration": 3375000,
          "text": {
            "Text": "一个",
            "Length": 2,
            "BoundaryType": "WordBoundary"
          }
        }
      }
    ]
  },
  {
    "Metadata": [
      {
        "Type": "WordBoundary",
        "Data": {
          "Offset": 154750000,
          "Duration": 4250000,
          "text": {
            "Text": "数字",
            "Length": 2,
            "BoundaryType": "WordBoundary"
          }
        }
      }
    ]
  },
  {
    "Metadata": [
      {
        "Type": "WordBoundary",
        "Data": {
          "Offset": 159125000,
          "Duration": 4000000,
          "text": {
            "Text": "营销",
            "Length": 2,
            "BoundaryType": "WordBoundary"
          }
        }
      }
    ]
  },
  {
    "Metadata": [
      {
        "Type": "WordBoundary",
        "Data": {
          "Offset": 163250000,
          "Duration": 3750000,
          "text": {
            "Text": "人员",
            "Length": 2,
            "BoundaryType": "WordBoundary"
          }
        }
      }
    ]
  },
  {
    "Metadata": [
      {
        "Type": "WordBoundary",
        "Data": {
          "Offset": 168000000,
          "Duration": 2125000,
          "text": {
            "Text": "用",
            "Length": 1,
            "BoundaryType": "WordBoundary"
          }
        }
      }
    ]
  },
  {
    "Metadata": [
      {
        "Type": "WordBoundary",
        "Data": {
          "Offset": 170125000,
          "Duration": 5875000,
          "text": {
            "Text": "OpenClaw",
            "Length": 8,
            "BoundaryType": "WordBoundary"
          }
        }
      }
    ]
  },
  {
    "Metadata": [
      {
        "Type": "WordBoundary",
        "Data": {
          "Offset": 177000000,
          "Duration": 3625000,
          "text": {
            "Text": "管理",
            "Length": 2,
            "BoundaryType": "WordBoundary"
          }
        }
      }
    ]
  },
  {
    "Metadata": [
      {
        "Type": "WordBoundary",
        "Data": {
          "Offset": 180875000,
          "Duration": 3625000,
          "text": {
            "Text": "客户",
            "Length": 2,
            "BoundaryType": "WordBoundary"
          }
        }
      }
    ]
  },
  {
    "Metadata": [
      {
        "Type": "WordBoundary",
        "Data": {
          "Offset": 184625000,
          "Duration": 3000000,
          "text": {
            "Text": "业务",
            "Length": 2,
            "BoundaryType": "WordBoundary"
          }
        }
      }
    ]
  },
  {
    "Metadata": [
      {
        "Type": "WordBoundary",
        "Data": {
          "Offset": 190750000,
          "Duration": 5125000,
          "text": {
            "Text": "相当于",
            "Length": 3,
            "BoundaryType": "WordBoundary"
          }
        }
      }
    ]
  },
  {
    "Metadata": [
      {
        "Type": "WordBoundary",
        "Data": {
          "Offset": 196125000,
          "Duration": 3000000,
          "text": {
            "Text": "一个",
            "Length": 2,
            "BoundaryType": "WordBoundary"
          }
        }
      }
    ]
  },
  {
    "Metadata": [
      {
        "Type": "WordBoundary",
        "Data": {
          "Offset": 199125000,
          "Duration": 2125000,
          "text": {
            "Text": "人",
            "Length": 1,
            "BoundaryType": "WordBoundary"
          }
        }
      }
    ]
  },
  {
    "Metadata": [
      {
        "Type": "WordBoundary",
        "Data": {
          "Offset": 201375000,
          "Duration": 3625000,
          "text": {
            "Text": "运营",
            "Length": 2,
            "BoundaryType": "WordBoundary"
          }
        }
      }
    ]
  },
  {
    "Metadata": [
      {
        "Type": "WordBoundary",
        "Data": {
          "Offset": 205250000,
          "Duration": 3875000,
          "text": {
            "Text": "整家",
            "Length": 2,
            "BoundaryType": "WordBoundary"
          }
        }
      }
    ]
  },
  {
    "Metadata": [
      {
        "Type": "WordBoundary",
        "Data": {
          "Offset": 209250000,
          "Duration": 3375000,
          "text": {
            "Text": "代理",
            "Length": 2,
            "BoundaryType": "WordBoundary"
          }
        }
      }
    ]
  },
  {
    "Metadata": [
      {
        "Type": "WordBoundary",
        "Data": {
          "Offset": 212750000,
          "Duration": 3875000,
          "text": {
            "Text": "公司",
            "Length": 2,
            "BoundaryType": "WordBoundary"
          }
        }
      }
    ]
  }
]